potrace/.gitignore
potrace/__init__.py
potrace/_potrace.pxd
potrace/_potrace.pyx
potrace/agg/__init__.py
potrace/agg/basics.pxd
potrace/agg/curves.pxd
potrace/agg/curves.pyx
potrace/bezier.pxd
potrace/bezier.pyx
potrace/_potrace.c
potrace/bezier.cpython-37m-x86_64-linux-gnu.so
potrace/bezier.cpp
potrace/_potrace.cpython-37m-x86_64-linux-gnu.so
potrace/agg/curves.cpp
potrace/agg/curves.cpython-37m-x86_64-linux-gnu.so
pypotrace-0.3.dist-info/LICENSE
pypotrace-0.3.dist-info/WHEEL
pypotrace-0.3.dist-info/METADATA
pypotrace-0.3.dist-info/RECORD
